itf.py
setup.py
itf.egg-info/PKG-INFO
itf.egg-info/SOURCES.txt
itf.egg-info/dependency_links.txt
itf.egg-info/entry_points.txt
itf.egg-info/pbr.json
itf.egg-info/requires.txt
itf.egg-info/top_level.txt