Metadata-Version: 1.0
Name: itf
Version: 2.4.0
Summary: Download Apple Music Festival 2015 Streams
Home-page: https://github.com/banteg/itf
Author: UNKNOWN
Author-email: UNKNOWN
License: UNKNOWN
Platform: UNKNOWN
